dems/__init__.py
dems/d1.py
dems/d2.py
dems/py.typed
dems-2025.6.1.dist-info/METADATA
dems-2025.6.1.dist-info/WHEEL
dems-2025.6.1.dist-info/licenses/LICENSE
dems-2025.6.1.dist-info/RECORD
