Metadata-Version: 2.4
Name: dems
Version: 2025.6.1
Summary: DESHIMA Measurement Set
Project-URL: homepage, https://github.com/deshima-dev/dems
Project-URL: repository, https://github.com/deshima-dev/dems
Author-email: Akio Taniguchi <taniguchi.akio@gmail.com>
License: MIT License
License-File: LICENSE
Keywords: astronomy,data-format,deshima,measurement-set,spectroscopy,submillimeter
Classifier: License :: OSI Approved :: MIT License
Classifier: Programming Language :: Python :: 3
Classifier: Programming Language :: Python :: 3.9
Classifier: Programming Language :: Python :: 3.10
Classifier: Programming Language :: Python :: 3.11
Classifier: Programming Language :: Python :: 3.12
Classifier: Programming Language :: Python :: 3.13
Requires-Python: <3.14,>=3.9
Requires-Dist: xarray-dataclasses<2.0,>=1.8
